PacGen-0.1.3.data/scripts/updatepac
pacgen/__init__.py
pacgen/pacgen.py
PacGen-0.1.3.dist-info/LICENSE
PacGen-0.1.3.dist-info/METADATA
PacGen-0.1.3.dist-info/WHEEL
PacGen-0.1.3.dist-info/top_level.txt
PacGen-0.1.3.dist-info/RECORD
