Metadata-Version: 2.1
Name: PacGen
Version: 0.1.3
Summary: UNKNOWN
Home-page: https://github.com/mehdipourfar/pacgen
License: MIT License
Platform: UNKNOWN
Requires-Dist: PyYAML
